{"trial_id": "0172", "hyperparameters": {"space": [{"class_name": "Choice", "config": {"name": "activation", "default": "relu", "conditions": [], "values": ["relu", "tanh", "sigmoid"], "ordered": false}}, {"class_name": "Int", "config": {"name": "first_units", "default": null, "conditions": [], "min_value": 10, "max_value": 100, "step": 5, "sampling": "linear"}}, {"class_name": "Int", "config": {"name": "num_layers", "default": null, "conditions": [], "min_value": 1, "max_value": 6, "step": 1, "sampling": "linear"}}, {"class_name": "Int", "config": {"name": "units_0", "default": null, "conditions": [], "min_value": 10, "max_value": 100, "step": 5, "sampling": "linear"}}, {"class_name": "Int", "config": {"name": "units_1", "default": null, "conditions": [], "min_value": 10, "max_value": 100, "step": 5, "sampling": "linear"}}, {"class_name": "Int", "config": {"name": "units_2", "default": null, "conditions": [], "min_value": 10, "max_value": 100, "step": 5, "sampling": "linear"}}, {"class_name": "Int", "config": {"name": "units_3", "default": null, "conditions": [], "min_value": 10, "max_value": 100, "step": 5, "sampling": "linear"}}, {"class_name": "Int", "config": {"name": "units_4", "default": null, "conditions": [], "min_value": 10, "max_value": 100, "step": 5, "sampling": "linear"}}, {"class_name": "Int", "config": {"name": "units_5", "default": null, "conditions": [], "min_value": 10, "max_value": 100, "step": 5, "sampling": "linear"}}], "values": {"activation": "sigmoid", "first_units": 20, "num_layers": 4, "units_0": 60, "units_1": 30, "units_2": 55, "units_3": 70, "units_4": 20, "units_5": 30, "tuner/epochs": 50, "tuner/initial_epoch": 17, "tuner/bracket": 1, "tuner/round": 1, "tuner/trial_id": "0164"}}, "metrics": {"metrics": {"loss": {"direction": "min", "observations": [{"value": [0.5523931384086609], "step": 13}]}, "accuracy": {"direction": "max", "observations": [{"value": [0.7313404083251953], "step": 13}]}, "val_loss": {"direction": "min", "observations": [{"value": [0.5514906644821167], "step": 13}]}, "val_accuracy": {"direction": "max", "observations": [{"value": [0.7331778407096863], "step": 13}]}}}, "score": 0.7331778407096863, "best_step": 13, "status": "COMPLETED", "message": null}